{
   "$schema": "http://json-schema.org/draft-07/schema",
   "$id": "#FAQHistory",
   "type": "object",
   "description": "The FAQ history object.",
   "properties": {
      "ArticleID": {
         "type": "integer",
         "readOnly": true
      },
      "Created": {
         "type": "string",
         "readOnly": true
      },
      "CreatedBy": {
         "type": "integer",
         "readOnly": true
      },
      "ID": {
         "type": "integer",
         "readOnly": true
      },
      "Name": {
         "type": "string",
         "readOnly": true
      }
   },
   "required" : [
      "ArticleID",
      "Created",
      "CreatedBy",
      "ID",
      "Name"
   ]
}
