{
   "$id" : "#ObjectIconPostRequest",
   "$schema" : "http://json-schema.org/draft-07/schema",
   "description" : "The object icon request object for creation.",
   "type" : "object",
   "properties" : {
      "ObjectIcon" : {
         "type" : "object",
         "properties" : {
            "Content" : {
               "type" : "string"
            },
            "ContentType" : {
               "type" : "string"
            },
            "Object" : {
               "type" : "string"
            },
            "ObjectID" : {
               "type" : "string"
            }
         },
         "required" : [
            "Content",
            "ContentType",
            "Object",
            "ObjectID"
         ]
      }
   },
   "required" : [
      "ObjectIcon"
   ]
}
