{
   "$id" : "#PermissionPatchRequest",
   "$schema" : "http://json-schema.org/schema",
   "description" : "The permission request object for update.",
   "type" : "object",
   "properties" : {
      "Permission" : {
         "type" : "object",
         "properties" : {
            "Comment" : {
               "type" : "string"
            },
            "IsRequired" : {
               "type" : "integer"
            },
            "Target" : {
               "type" : "string"
            },
            "TypeID" : {
               "type" : "integer"
            },
            "Value" : {
               "description" : "bitmask, please see documentation for bit descriptions",
               "type" : "integer"
            }
         }
      }
   },
   "required" : [
      "Permission"
   ]
}
