{
    "ConfigItemVersion": [
        {
            "CurInciState": "Operational",
            "CreateBy": 1,
            "Class": "Computer",
            "CurInciStateType": "operational",
            "InciStateID": 1,
            "InciStateType": "operational",
            "ConfigItemID": "82",
            "CurDeplStateID": 32,
            "Name": "test ci",
            "InciState": "Operational",
            "CurDeplState": "Production",
            "DeplState": "Production",
            "ClassID": "22",
            "Number": "1022000022",
            "DeplStateID": 32,
            "VersionID": 561,
            "CreateTime": "2018-08-01 12:42:18",
            "CurDeplStateType": "productive",
            "DeplStateType": "productive",
            "CurInciStateID": 1
        },
        {
            "InciStateID": 1,
            "CurInciState": "Operational",
            "CreateBy": 1,
            "CurInciStateType": "operational",
            "Class": "Computer",
            "ConfigItemID": "82",
            "InciStateType": "operational",
            "CurDeplStateID": 32,
            "Name": "test ci 2",
            "InciState": "Operational",
            "CurDeplState": "Production",
            "ClassID": "22",
            "DeplState": "Production",
            "DeplStateID": 32,
            "VersionID": 562,
            "Number": "1022000022",
            "CreateTime": "2018-08-01 15:57:55",
            "CurDeplStateType": "productive",
            "CurInciStateID": 1,
            "DeplStateType": "productive"
        }
    ]
}